[{"object":"block","id":"38034d6d-7cea-816f-aa6a-ed4c7904c148","parent":{"type":"page_id","page_id":"38034d6d-7cea-81bd-9ff4-ff0a324e4d5a"},"created_time":"2026-06-15T15:20:00.000Z","last_edited_time":"2026-06-15T15:20:00.000Z","created_by":{"object":"user","id":"35534d6d-7cea-8179-8809-002768bc44c3"},"last_edited_by":{"object":"user","id":"35534d6d-7cea-8179-8809-002768bc44c3"},"has_children":false,"in_trash":false,"type":"paragraph","paragraph":{"rich_text":[{"type":"text","text":{"content":"Радиальная конструкция шин для погрузчиков с бортовым поворотом, обеспечивающая большую опорную поверхность, лучшую устойчивость и более лучшее сцепление по сравнению с диагональной конструкцией. Агрессивный рисунок протектора R4 для областей применения, требующих хорошего сцепления","link":null},"annotations":{"bold":false,"italic":false,"strikethrough":false,"underline":false,"code":false,"color":"default"},"plain_text":"Радиальная конструкция шин для погрузчиков с бортовым поворотом, обеспечивающая большую опорную поверхность, лучшую устойчивость и более лучшее сцепление по сравнению с диагональной конструкцией. Агрессивный рисунок протектора R4 для областей применения, требующих хорошего сцепления","href":null}],"icon":null,"color":"default"},"archived":false},{"object":"block","id":"38034d6d-7cea-81bd-b8db-e32721a883a0","parent":{"type":"page_id","page_id":"38034d6d-7cea-81bd-9ff4-ff0a324e4d5a"},"created_time":"2026-06-15T15:20:00.000Z","last_edited_time":"2026-06-15T15:20:00.000Z","created_by":{"object":"user","id":"35534d6d-7cea-8179-8809-002768bc44c3"},"last_edited_by":{"object":"user","id":"35534d6d-7cea-8179-8809-002768bc44c3"},"has_children":false,"in_trash":false,"type":"heading_2","heading_2":{"rich_text":[{"type":"text","text":{"content":"Features","link":null},"annotations":{"bold":false,"italic":false,"strikethrough":false,"underline":false,"code":false,"color":"default"},"plain_text":"Features","href":null}],"is_toggleable":false,"color":"default"},"archived":false},{"object":"block","id":"38034d6d-7cea-8180-bc4b-c973b26a2dfb","parent":{"type":"page_id","page_id":"38034d6d-7cea-81bd-9ff4-ff0a324e4d5a"},"created_time":"2026-06-15T15:20:00.000Z","last_edited_time":"2026-06-15T15:20:00.000Z","created_by":{"object":"user","id":"35534d6d-7cea-8179-8809-002768bc44c3"},"last_edited_by":{"object":"user","id":"35534d6d-7cea-8179-8809-002768bc44c3"},"has_children":false,"in_trash":false,"type":"bulleted_list_item","bulleted_list_item":{"rich_text":[{"type":"text","text":{"content":"Радиальная цельнометаллокордная конструкция обеспечивает лучшие эксплуатационные характеристики по сравнению с диагональной","link":null},"annotations":{"bold":false,"italic":false,"strikethrough":false,"underline":false,"code":false,"color":"default"},"plain_text":"Радиальная цельнометаллокордная конструкция обеспечивает лучшие эксплуатационные характеристики по сравнению с диагональной","href":null}],"color":"default"},"archived":false},{"object":"block","id":"38034d6d-7cea-818f-89bc-e6c7d7887f78","parent":{"type":"page_id","page_id":"38034d6d-7cea-81bd-9ff4-ff0a324e4d5a"},"created_time":"2026-06-15T15:20:00.000Z","last_edited_time":"2026-06-15T15:20:00.000Z","created_by":{"object":"user","id":"35534d6d-7cea-8179-8809-002768bc44c3"},"last_edited_by":{"object":"user","id":"35534d6d-7cea-8179-8809-002768bc44c3"},"has_children":false,"in_trash":false,"type":"bulleted_list_item","bulleted_list_item":{"rich_text":[{"type":"text","text":{"content":"Стальные брекеры защищают от проколов","link":null},"annotations":{"bold":false,"italic":false,"strikethrough":false,"underline":false,"code":false,"color":"default"},"plain_text":"Стальные брекеры защищают от проколов","href":null}],"color":"default"},"archived":false},{"object":"block","id":"38034d6d-7cea-81d1-82d2-f384452bde7d","parent":{"type":"page_id","page_id":"38034d6d-7cea-81bd-9ff4-ff0a324e4d5a"},"created_time":"2026-06-15T15:20:00.000Z","last_edited_time":"2026-06-15T15:20:00.000Z","created_by":{"object":"user","id":"35534d6d-7cea-8179-8809-002768bc44c3"},"last_edited_by":{"object":"user","id":"35534d6d-7cea-8179-8809-002768bc44c3"},"has_children":false,"in_trash":false,"type":"bulleted_list_item","bulleted_list_item":{"rich_text":[{"type":"text","text":{"content":"Широкий рисунок протектора для повышения проходимости","link":null},"annotations":{"bold":false,"italic":false,"strikethrough":false,"underline":false,"code":false,"color":"default"},"plain_text":"Широкий рисунок протектора для повышения проходимости","href":null}],"color":"default"},"archived":false},{"object":"block","id":"38034d6d-7cea-81c5-a7bb-c2b318e13ba0","parent":{"type":"page_id","page_id":"38034d6d-7cea-81bd-9ff4-ff0a324e4d5a"},"created_time":"2026-06-15T15:20:00.000Z","last_edited_time":"2026-06-15T15:20:00.000Z","created_by":{"object":"user","id":"35534d6d-7cea-8179-8809-002768bc44c3"},"last_edited_by":{"object":"user","id":"35534d6d-7cea-8179-8809-002768bc44c3"},"has_children":false,"in_trash":false,"type":"bulleted_list_item","bulleted_list_item":{"rich_text":[{"type":"text","text":{"content":"Устойчивый к порезам и износу компаунд","link":null},"annotations":{"bold":false,"italic":false,"strikethrough":false,"underline":false,"code":false,"color":"default"},"plain_text":"Устойчивый к порезам и износу компаунд","href":null}],"color":"default"},"archived":false},{"object":"block","id":"38034d6d-7cea-81f9-af03-ff11c46df4bf","parent":{"type":"page_id","page_id":"38034d6d-7cea-81bd-9ff4-ff0a324e4d5a"},"created_time":"2026-06-15T15:20:00.000Z","last_edited_time":"2026-06-15T15:20:00.000Z","created_by":{"object":"user","id":"35534d6d-7cea-8179-8809-002768bc44c3"},"last_edited_by":{"object":"user","id":"35534d6d-7cea-8179-8809-002768bc44c3"},"has_children":false,"in_trash":false,"type":"bulleted_list_item","bulleted_list_item":{"rich_text":[{"type":"text","text":{"content":"Усиленные борт и боковина обеспечивают отличную устойчивость","link":null},"annotations":{"bold":false,"italic":false,"strikethrough":false,"underline":false,"code":false,"color":"default"},"plain_text":"Усиленные борт и боковина обеспечивают отличную устойчивость","href":null}],"color":"default"},"archived":false},{"object":"block","id":"38034d6d-7cea-810d-af86-eddbd95a7b9e","parent":{"type":"page_id","page_id":"38034d6d-7cea-81bd-9ff4-ff0a324e4d5a"},"created_time":"2026-06-15T15:20:00.000Z","last_edited_time":"2026-06-15T15:20:00.000Z","created_by":{"object":"user","id":"35534d6d-7cea-8179-8809-002768bc44c3"},"last_edited_by":{"object":"user","id":"35534d6d-7cea-8179-8809-002768bc44c3"},"has_children":false,"in_trash":false,"type":"heading_2","heading_2":{"rich_text":[{"type":"text","text":{"content":"Specifications","link":null},"annotations":{"bold":false,"italic":false,"strikethrough":false,"underline":false,"code":false,"color":"default"},"plain_text":"Specifications","href":null}],"is_toggleable":false,"color":"default"},"archived":false},{"object":"block","id":"38034d6d-7cea-8143-990c-f38c5a529acc","parent":{"type":"page_id","page_id":"38034d6d-7cea-81bd-9ff4-ff0a324e4d5a"},"created_time":"2026-06-15T15:20:00.000Z","last_edited_time":"2026-06-15T15:20:00.000Z","created_by":{"object":"user","id":"35534d6d-7cea-8179-8809-002768bc44c3"},"last_edited_by":{"object":"user","id":"35534d6d-7cea-8179-8809-002768bc44c3"},"has_children":true,"in_trash":false,"type":"table","table":{"table_width":10,"has_column_header":false,"has_row_header":false},"archived":false,"children":[{"object":"block","id":"38034d6d-7cea-81aa-9122-e36eb9524f8d","parent":{"type":"block_id","block_id":"38034d6d-7cea-8143-990c-f38c5a529acc"},"created_time":"2026-06-15T15:20:00.000Z","last_edited_time":"2026-06-15T15:20:00.000Z","created_by":{"object":"user","id":"35534d6d-7cea-8179-8809-002768bc44c3"},"last_edited_by":{"object":"user","id":"35534d6d-7cea-8179-8809-002768bc44c3"},"has_children":false,"in_trash":false,"type":"table_row","table_row":{"cells":[[],[],[],[{"type":"text","text":{"content":"in","link":null},"annotations":{"bold":false,"italic":false,"strikethrough":false,"underline":false,"code":false,"color":"default"},"plain_text":"in","href":null}],[{"type":"text","text":{"content":"in","link":null},"annotations":{"bold":false,"italic":false,"strikethrough":false,"underline":false,"code":false,"color":"default"},"plain_text":"in","href":null}],[{"type":"text","text":{"content":"32nds","link":null},"annotations":{"bold":false,"italic":false,"strikethrough":false,"underline":false,"code":false,"color":"default"},"plain_text":"32nds","href":null}],[{"type":"text","text":{"content":"mph","link":null},"annotations":{"bold":false,"italic":false,"strikethrough":false,"underline":false,"code":false,"color":"default"},"plain_text":"mph","href":null}],[{"type":"text","text":{"content":"psi","link":null},"annotations":{"bold":false,"italic":false,"strikethrough":false,"underline":false,"code":false,"color":"default"},"plain_text":"psi","href":null}],[{"type":"text","text":{"content":"lbs","link":null},"annotations":{"bold":false,"italic":false,"strikethrough":false,"underline":false,"code":false,"color":"default"},"plain_text":"lbs","href":null}],[]]},"archived":false},{"object":"block","id":"38034d6d-7cea-8101-a85b-fad4bbee9299","parent":{"type":"block_id","block_id":"38034d6d-7cea-8143-990c-f38c5a529acc"},"created_time":"2026-06-15T15:20:00.000Z","last_edited_time":"2026-06-15T15:20:00.000Z","created_by":{"object":"user","id":"35534d6d-7cea-8179-8809-002768bc44c3"},"last_edited_by":{"object":"user","id":"35534d6d-7cea-8179-8809-002768bc44c3"},"has_children":false,"in_trash":false,"type":"table_row","table_row":{"cells":[[],[],[],[{"type":"text","text":{"content":"mm","link":null},"annotations":{"bold":false,"italic":false,"strikethrough":false,"underline":false,"code":false,"color":"default"},"plain_text":"mm","href":null}],[{"type":"text","text":{"content":"mm","link":null},"annotations":{"bold":false,"italic":false,"strikethrough":false,"underline":false,"code":false,"color":"default"},"plain_text":"mm","href":null}],[{"type":"text","text":{"content":"mm","link":null},"annotations":{"bold":false,"italic":false,"strikethrough":false,"underline":false,"code":false,"color":"default"},"plain_text":"mm","href":null}],[{"type":"text","text":{"content":"kph","link":null},"annotations":{"bold":false,"italic":false,"strikethrough":false,"underline":false,"code":false,"color":"default"},"plain_text":"kph","href":null}],[{"type":"text","text":{"content":"KPa","link":null},"annotations":{"bold":false,"italic":false,"strikethrough":false,"underline":false,"code":false,"color":"default"},"plain_text":"KPa","href":null}],[{"type":"text","text":{"content":"kg","link":null},"annotations":{"bold":false,"italic":false,"strikethrough":false,"underline":false,"code":false,"color":"default"},"plain_text":"kg","href":null}],[]]},"archived":false},{"object":"block","id":"38034d6d-7cea-8187-8143-e9927021b807","parent":{"type":"block_id","block_id":"38034d6d-7cea-8143-990c-f38c5a529acc"},"created_time":"2026-06-15T15:20:00.000Z","last_edited_time":"2026-06-15T15:20:00.000Z","created_by":{"object":"user","id":"35534d6d-7cea-8179-8809-002768bc44c3"},"last_edited_by":{"object":"user","id":"35534d6d-7cea-8179-8809-002768bc44c3"},"has_children":false,"in_trash":false,"type":"table_row","table_row":{"cells":[[{"type":"text","text":{"content":"31x15.50R15","link":null},"annotations":{"bold":false,"italic":false,"strikethrough":false,"underline":false,"code":false,"color":"default"},"plain_text":"31x15.50R15","href":null}],[{"type":"text","text":{"content":"TL","link":null},"annotations":{"bold":false,"italic":false,"strikethrough":false,"underline":false,"code":false,"color":"default"},"plain_text":"TL","href":null}],[{"type":"text","text":{"content":"13LB","link":null},"annotations":{"bold":false,"italic":false,"strikethrough":false,"underline":false,"code":false,"color":"default"},"plain_text":"13LB","href":null}],[{"type":"text","text":{"content":"31.0","link":null},"annotations":{"bold":false,"italic":false,"strikethrough":false,"underline":false,"code":false,"color":"default"},"plain_text":"31.0","href":null}],[{"type":"text","text":{"content":"15.1","link":null},"annotations":{"bold":false,"italic":false,"strikethrough":false,"underline":false,"code":false,"color":"default"},"plain_text":"15.1","href":null}],[{"type":"text","text":{"content":"30","link":null},"annotations":{"bold":false,"italic":false,"strikethrough":false,"underline":false,"code":false,"color":"default"},"plain_text":"30","href":null}],[{"type":"text","text":{"content":"5","link":null},"annotations":{"bold":false,"italic":false,"strikethrough":false,"underline":false,"code":false,"color":"default"},"plain_text":"5","href":null}],[{"type":"text","text":{"content":"45","link":null},"annotations":{"bold":false,"italic":false,"strikethrough":false,"underline":false,"code":false,"color":"default"},"plain_text":"45","href":null}],[{"type":"text","text":{"content":"4400","link":null},"annotations":{"bold":false,"italic":false,"strikethrough":false,"underline":false,"code":false,"color":"default"},"plain_text":"4400","href":null}],[{"type":"text","text":{"content":"132A2","link":null},"annotations":{"bold":false,"italic":false,"strikethrough":false,"underline":false,"code":false,"color":"default"},"plain_text":"132A2","href":null}]]},"archived":false},{"object":"block","id":"38034d6d-7cea-817c-86ac-f8f433219872","parent":{"type":"block_id","block_id":"38034d6d-7cea-8143-990c-f38c5a529acc"},"created_time":"2026-06-15T15:20:00.000Z","last_edited_time":"2026-06-15T15:20:00.000Z","created_by":{"object":"user","id":"35534d6d-7cea-8179-8809-002768bc44c3"},"last_edited_by":{"object":"user","id":"35534d6d-7cea-8179-8809-002768bc44c3"},"has_children":false,"in_trash":false,"type":"table_row","table_row":{"cells":[[{"type":"text","text":{"content":"31x15.50R15","link":null},"annotations":{"bold":false,"italic":false,"strikethrough":false,"underline":false,"code":false,"color":"default"},"plain_text":"31x15.50R15","href":null}],[{"type":"text","text":{"content":"TL","link":null},"annotations":{"bold":false,"italic":false,"strikethrough":false,"underline":false,"code":false,"color":"default"},"plain_text":"TL","href":null}],[{"type":"text","text":{"content":"13LB","link":null},"annotations":{"bold":false,"italic":false,"strikethrough":false,"underline":false,"code":false,"color":"default"},"plain_text":"13LB","href":null}],[{"type":"text","text":{"content":"787","link":null},"annotations":{"bold":false,"italic":false,"strikethrough":false,"underline":false,"code":false,"color":"default"},"plain_text":"787","href":null}],[{"type":"text","text":{"content":"384","link":null},"annotations":{"bold":false,"italic":false,"strikethrough":false,"underline":false,"code":false,"color":"default"},"plain_text":"384","href":null}],[{"type":"text","text":{"content":"23","link":null},"annotations":{"bold":false,"italic":false,"strikethrough":false,"underline":false,"code":false,"color":"default"},"plain_text":"23","href":null}],[{"type":"text","text":{"content":"10","link":null},"annotations":{"bold":false,"italic":false,"strikethrough":false,"underline":false,"code":false,"color":"default"},"plain_text":"10","href":null}],[{"type":"text","text":{"content":"310","link":null},"annotations":{"bold":false,"italic":false,"strikethrough":false,"underline":false,"code":false,"color":"default"},"plain_text":"310","href":null}],[{"type":"text","text":{"content":"2000","link":null},"annotations":{"bold":false,"italic":false,"strikethrough":false,"underline":false,"code":false,"color":"default"},"plain_text":"2000","href":null}],[{"type":"text","text":{"content":"132A2","link":null},"annotations":{"bold":false,"italic":false,"strikethrough":false,"underline":false,"code":false,"color":"default"},"plain_text":"132A2","href":null}]]},"archived":false},{"object":"block","id":"38034d6d-7cea-8133-91f5-e52e67579306","parent":{"type":"block_id","block_id":"38034d6d-7cea-8143-990c-f38c5a529acc"},"created_time":"2026-06-15T15:20:00.000Z","last_edited_time":"2026-06-15T15:20:00.000Z","created_by":{"object":"user","id":"35534d6d-7cea-8179-8809-002768bc44c3"},"last_edited_by":{"object":"user","id":"35534d6d-7cea-8179-8809-002768bc44c3"},"has_children":false,"in_trash":false,"type":"table_row","table_row":{"cells":[[{"type":"text","text":{"content":"10R16.5","link":null},"annotations":{"bold":false,"italic":false,"strikethrough":false,"underline":false,"code":false,"color":"default"},"plain_text":"10R16.5","href":null}],[{"type":"text","text":{"content":"TL","link":null},"annotations":{"bold":false,"italic":false,"strikethrough":false,"underline":false,"code":false,"color":"default"},"plain_text":"TL","href":null}],[{"type":"text","text":{"content":"8.25","link":null},"annotations":{"bold":false,"italic":false,"strikethrough":false,"underline":false,"code":false,"color":"default"},"plain_text":"8.25","href":null}],[{"type":"text","text":{"content":"30.6","link":null},"annotations":{"bold":false,"italic":false,"strikethrough":false,"underline":false,"code":false,"color":"default"},"plain_text":"30.6","href":null}],[{"type":"text","text":{"content":"10.3","link":null},"annotations":{"bold":false,"italic":false,"strikethrough":false,"underline":false,"code":false,"color":"default"},"plain_text":"10.3","href":null}],[{"type":"text","text":{"content":"25","link":null},"annotations":{"bold":false,"italic":false,"strikethrough":false,"underline":false,"code":false,"color":"default"},"plain_text":"25","href":null}],[{"type":"text","text":{"content":"5","link":null},"annotations":{"bold":false,"italic":false,"strikethrough":false,"underline":false,"code":false,"color":"default"},"plain_text":"5","href":null}],[{"type":"text","text":{"content":"75","link":null},"annotations":{"bold":false,"italic":false,"strikethrough":false,"underline":false,"code":false,"color":"default"},"plain_text":"75","href":null}],[{"type":"text","text":{"content":"4680","link":null},"annotations":{"bold":false,"italic":false,"strikethrough":false,"underline":false,"code":false,"color":"default"},"plain_text":"4680","href":null}],[{"type":"text","text":{"content":"134A2","link":null},"annotations":{"bold":false,"italic":false,"strikethrough":false,"underline":false,"code":false,"color":"default"},"plain_text":"134A2","href":null}]]},"archived":false},{"object":"block","id":"38034d6d-7cea-8108-8680-f52c0145280b","parent":{"type":"block_id","block_id":"38034d6d-7cea-8143-990c-f38c5a529acc"},"created_time":"2026-06-15T15:20:00.000Z","last_edited_time":"2026-06-15T15:20:00.000Z","created_by":{"object":"user","id":"35534d6d-7cea-8179-8809-002768bc44c3"},"last_edited_by":{"object":"user","id":"35534d6d-7cea-8179-8809-002768bc44c3"},"has_children":false,"in_trash":false,"type":"table_row","table_row":{"cells":[[{"type":"text","text":{"content":"10R16.5","link":null},"annotations":{"bold":false,"italic":false,"strikethrough":false,"underline":false,"code":false,"color":"default"},"plain_text":"10R16.5","href":null}],[{"type":"text","text":{"content":"TL","link":null},"annotations":{"bold":false,"italic":false,"strikethrough":false,"underline":false,"code":false,"color":"default"},"plain_text":"TL","href":null}],[{"type":"text","text":{"content":"8.25","link":null},"annotations":{"bold":false,"italic":false,"strikethrough":false,"underline":false,"code":false,"color":"default"},"plain_text":"8.25","href":null}],[{"type":"text","text":{"content":"778","link":null},"annotations":{"bold":false,"italic":false,"strikethrough":false,"underline":false,"code":false,"color":"default"},"plain_text":"778","href":null}],[{"type":"text","text":{"content":"261","link":null},"annotations":{"bold":false,"italic":false,"strikethrough":false,"underline":false,"code":false,"color":"default"},"plain_text":"261","href":null}],[{"type":"text","text":{"content":"20","link":null},"annotations":{"bold":false,"italic":false,"strikethrough":false,"underline":false,"code":false,"color":"default"},"plain_text":"20","href":null}],[{"type":"text","text":{"content":"10","link":null},"annotations":{"bold":false,"italic":false,"strikethrough":false,"underline":false,"code":false,"color":"default"},"plain_text":"10","href":null}],[{"type":"text","text":{"content":"520","link":null},"annotations":{"bold":false,"italic":false,"strikethrough":false,"underline":false,"code":false,"color":"default"},"plain_text":"520","href":null}],[{"type":"text","text":{"content":"2120","link":null},"annotations":{"bold":false,"italic":false,"strikethrough":false,"underline":false,"code":false,"color":"default"},"plain_text":"2120","href":null}],[{"type":"text","text":{"content":"134A2","link":null},"annotations":{"bold":false,"italic":false,"strikethrough":false,"underline":false,"code":false,"color":"default"},"plain_text":"134A2","href":null}]]},"archived":false},{"object":"block","id":"38034d6d-7cea-81ae-9e65-c8e21824390e","parent":{"type":"block_id","block_id":"38034d6d-7cea-8143-990c-f38c5a529acc"},"created_time":"2026-06-15T15:20:00.000Z","last_edited_time":"2026-06-15T15:20:00.000Z","created_by":{"object":"user","id":"35534d6d-7cea-8179-8809-002768bc44c3"},"last_edited_by":{"object":"user","id":"35534d6d-7cea-8179-8809-002768bc44c3"},"has_children":false,"in_trash":false,"type":"table_row","table_row":{"cells":[[{"type":"text","text":{"content":"12R16.5","link":null},"annotations":{"bold":false,"italic":false,"strikethrough":false,"underline":false,"code":false,"color":"default"},"plain_text":"12R16.5","href":null}],[{"type":"text","text":{"content":"TL","link":null},"annotations":{"bold":false,"italic":false,"strikethrough":false,"underline":false,"code":false,"color":"default"},"plain_text":"TL","href":null}],[{"type":"text","text":{"content":"9.75","link":null},"annotations":{"bold":false,"italic":false,"strikethrough":false,"underline":false,"code":false,"color":"default"},"plain_text":"9.75","href":null}],[{"type":"text","text":{"content":"32.9","link":null},"annotations":{"bold":false,"italic":false,"strikethrough":false,"underline":false,"code":false,"color":"default"},"plain_text":"32.9","href":null}],[{"type":"text","text":{"content":"11.9","link":null},"annotations":{"bold":false,"italic":false,"strikethrough":false,"underline":false,"code":false,"color":"default"},"plain_text":"11.9","href":null}],[{"type":"text","text":{"content":"30","link":null},"annotations":{"bold":false,"italic":false,"strikethrough":false,"underline":false,"code":false,"color":"default"},"plain_text":"30","href":null}],[{"type":"text","text":{"content":"5","link":null},"annotations":{"bold":false,"italic":false,"strikethrough":false,"underline":false,"code":false,"color":"default"},"plain_text":"5","href":null}],[{"type":"text","text":{"content":"80","link":null},"annotations":{"bold":false,"italic":false,"strikethrough":false,"underline":false,"code":false,"color":"default"},"plain_text":"80","href":null}],[{"type":"text","text":{"content":"6400","link":null},"annotations":{"bold":false,"italic":false,"strikethrough":false,"underline":false,"code":false,"color":"default"},"plain_text":"6400","href":null}],[{"type":"text","text":{"content":"145A2","link":null},"annotations":{"bold":false,"italic":false,"strikethrough":false,"underline":false,"code":false,"color":"default"},"plain_text":"145A2","href":null}]]},"archived":false},{"object":"block","id":"38034d6d-7cea-81e2-b887-f2048b61f471","parent":{"type":"block_id","block_id":"38034d6d-7cea-8143-990c-f38c5a529acc"},"created_time":"2026-06-15T15:20:00.000Z","last_edited_time":"2026-06-15T15:20:00.000Z","created_by":{"object":"user","id":"35534d6d-7cea-8179-8809-002768bc44c3"},"last_edited_by":{"object":"user","id":"35534d6d-7cea-8179-8809-002768bc44c3"},"has_children":false,"in_trash":false,"type":"table_row","table_row":{"cells":[[{"type":"text","text":{"content":"12R16.5","link":null},"annotations":{"bold":false,"italic":false,"strikethrough":false,"underline":false,"code":false,"color":"default"},"plain_text":"12R16.5","href":null}],[{"type":"text","text":{"content":"TL","link":null},"annotations":{"bold":false,"italic":false,"strikethrough":false,"underline":false,"code":false,"color":"default"},"plain_text":"TL","href":null}],[{"type":"text","text":{"content":"9.75","link":null},"annotations":{"bold":false,"italic":false,"strikethrough":false,"underline":false,"code":false,"color":"default"},"plain_text":"9.75","href":null}],[{"type":"text","text":{"content":"835","link":null},"annotations":{"bold":false,"italic":false,"strikethrough":false,"underline":false,"code":false,"color":"default"},"plain_text":"835","href":null}],[{"type":"text","text":{"content":"301","link":null},"annotations":{"bold":false,"italic":false,"strikethrough":false,"underline":false,"code":false,"color":"default"},"plain_text":"301","href":null}],[{"type":"text","text":{"content":"23","link":null},"annotations":{"bold":false,"italic":false,"strikethrough":false,"underline":false,"code":false,"color":"default"},"plain_text":"23","href":null}],[{"type":"text","text":{"content":"10","link":null},"annotations":{"bold":false,"italic":false,"strikethrough":false,"underline":false,"code":false,"color":"default"},"plain_text":"10","href":null}],[{"type":"text","text":{"content":"550","link":null},"annotations":{"bold":false,"italic":false,"strikethrough":false,"underline":false,"code":false,"color":"default"},"plain_text":"550","href":null}],[{"type":"text","text":{"content":"2900","link":null},"annotations":{"bold":false,"italic":false,"strikethrough":false,"underline":false,"code":false,"color":"default"},"plain_text":"2900","href":null}],[{"type":"text","text":{"content":"145A2","link":null},"annotations":{"bold":false,"italic":false,"strikethrough":false,"underline":false,"code":false,"color":"default"},"plain_text":"145A2","href":null}]]},"archived":false},{"object":"block","id":"38034d6d-7cea-81cc-9d97-c231459a755e","parent":{"type":"block_id","block_id":"38034d6d-7cea-8143-990c-f38c5a529acc"},"created_time":"2026-06-15T15:20:00.000Z","last_edited_time":"2026-06-15T15:20:00.000Z","created_by":{"object":"user","id":"35534d6d-7cea-8179-8809-002768bc44c3"},"last_edited_by":{"object":"user","id":"35534d6d-7cea-8179-8809-002768bc44c3"},"has_children":false,"in_trash":false,"type":"table_row","table_row":{"cells":[[{"type":"text","text":{"content":"14R17.5","link":null},"annotations":{"bold":false,"italic":false,"strikethrough":false,"underline":false,"code":false,"color":"default"},"plain_text":"14R17.5","href":null}],[{"type":"text","text":{"content":"TL","link":null},"annotations":{"bold":false,"italic":false,"strikethrough":false,"underline":false,"code":false,"color":"default"},"plain_text":"TL","href":null}],[{"type":"text","text":{"content":"10.50","link":null},"annotations":{"bold":false,"italic":false,"strikethrough":false,"underline":false,"code":false,"color":"default"},"plain_text":"10.50","href":null}],[{"type":"text","text":{"content":"36.4","link":null},"annotations":{"bold":false,"italic":false,"strikethrough":false,"underline":false,"code":false,"color":"default"},"plain_text":"36.4","href":null}],[{"type":"text","text":{"content":"13.8","link":null},"annotations":{"bold":false,"italic":false,"strikethrough":false,"underline":false,"code":false,"color":"default"},"plain_text":"13.8","href":null}],[{"type":"text","text":{"content":"34","link":null},"annotations":{"bold":false,"italic":false,"strikethrough":false,"underline":false,"code":false,"color":"default"},"plain_text":"34","href":null}],[{"type":"text","text":{"content":"5","link":null},"annotations":{"bold":false,"italic":false,"strikethrough":false,"underline":false,"code":false,"color":"default"},"plain_text":"5","href":null}],[{"type":"text","text":{"content":"80","link":null},"annotations":{"bold":false,"italic":false,"strikethrough":false,"underline":false,"code":false,"color":"default"},"plain_text":"80","href":null}],[{"type":"text","text":{"content":"8550","link":null},"annotations":{"bold":false,"italic":false,"strikethrough":false,"underline":false,"code":false,"color":"default"},"plain_text":"8550","href":null}],[{"type":"text","text":{"content":"155A2","link":null},"annotations":{"bold":false,"italic":false,"strikethrough":false,"underline":false,"code":false,"color":"default"},"plain_text":"155A2","href":null}]]},"archived":false},{"object":"block","id":"38034d6d-7cea-8161-8c38-f880c5cff274","parent":{"type":"block_id","block_id":"38034d6d-7cea-8143-990c-f38c5a529acc"},"created_time":"2026-06-15T15:20:00.000Z","last_edited_time":"2026-06-15T15:20:00.000Z","created_by":{"object":"user","id":"35534d6d-7cea-8179-8809-002768bc44c3"},"last_edited_by":{"object":"user","id":"35534d6d-7cea-8179-8809-002768bc44c3"},"has_children":false,"in_trash":false,"type":"table_row","table_row":{"cells":[[{"type":"text","text":{"content":"14R17.5","link":null},"annotations":{"bold":false,"italic":false,"strikethrough":false,"underline":false,"code":false,"color":"default"},"plain_text":"14R17.5","href":null}],[{"type":"text","text":{"content":"TL","link":null},"annotations":{"bold":false,"italic":false,"strikethrough":false,"underline":false,"code":false,"color":"default"},"plain_text":"TL","href":null}],[{"type":"text","text":{"content":"10.50","link":null},"annotations":{"bold":false,"italic":false,"strikethrough":false,"underline":false,"code":false,"color":"default"},"plain_text":"10.50","href":null}],[{"type":"text","text":{"content":"925","link":null},"annotations":{"bold":false,"italic":false,"strikethrough":false,"underline":false,"code":false,"color":"default"},"plain_text":"925","href":null}],[{"type":"text","text":{"content":"350","link":null},"annotations":{"bold":false,"italic":false,"strikethrough":false,"underline":false,"code":false,"color":"default"},"plain_text":"350","href":null}],[{"type":"text","text":{"content":"27","link":null},"annotations":{"bold":false,"italic":false,"strikethrough":false,"underline":false,"code":false,"color":"default"},"plain_text":"27","href":null}],[{"type":"text","text":{"content":"10","link":null},"annotations":{"bold":false,"italic":false,"strikethrough":false,"underline":false,"code":false,"color":"default"},"plain_text":"10","href":null}],[{"type":"text","text":{"content":"550","link":null},"annotations":{"bold":false,"italic":false,"strikethrough":false,"underline":false,"code":false,"color":"default"},"plain_text":"550","href":null}],[{"type":"text","text":{"content":"3875","link":null},"annotations":{"bold":false,"italic":false,"strikethrough":false,"underline":false,"code":false,"color":"default"},"plain_text":"3875","href":null}],[{"type":"text","text":{"content":"155A2","link":null},"annotations":{"bold":false,"italic":false,"strikethrough":false,"underline":false,"code":false,"color":"default"},"plain_text":"155A2","href":null}]]},"archived":false},{"object":"block","id":"38034d6d-7cea-8196-becd-cab8e7084524","parent":{"type":"block_id","block_id":"38034d6d-7cea-8143-990c-f38c5a529acc"},"created_time":"2026-06-15T15:20:00.000Z","last_edited_time":"2026-06-15T15:20:00.000Z","created_by":{"object":"user","id":"35534d6d-7cea-8179-8809-002768bc44c3"},"last_edited_by":{"object":"user","id":"35534d6d-7cea-8179-8809-002768bc44c3"},"has_children":false,"in_trash":false,"type":"table_row","table_row":{"cells":[[{"type":"text","text":{"content":"15R19.5","link":null},"annotations":{"bold":false,"italic":false,"strikethrough":false,"underline":false,"code":false,"color":"default"},"plain_text":"15R19.5","href":null}],[{"type":"text","text":{"content":"TL","link":null},"annotations":{"bold":false,"italic":false,"strikethrough":false,"underline":false,"code":false,"color":"default"},"plain_text":"TL","href":null}],[{"type":"text","text":{"content":"11.75","link":null},"annotations":{"bold":false,"italic":false,"strikethrough":false,"underline":false,"code":false,"color":"default"},"plain_text":"11.75","href":null}],[{"type":"text","text":{"content":"40.1","link":null},"annotations":{"bold":false,"italic":false,"strikethrough":false,"underline":false,"code":false,"color":"default"},"plain_text":"40.1","href":null}],[{"type":"text","text":{"content":"15.3","link":null},"annotations":{"bold":false,"italic":false,"strikethrough":false,"underline":false,"code":false,"color":"default"},"plain_text":"15.3","href":null}],[{"type":"text","text":{"content":"33","link":null},"annotations":{"bold":false,"italic":false,"strikethrough":false,"underline":false,"code":false,"color":"default"},"plain_text":"33","href":null}],[{"type":"text","text":{"content":"5","link":null},"annotations":{"bold":false,"italic":false,"strikethrough":false,"underline":false,"code":false,"color":"default"},"plain_text":"5","href":null}],[{"type":"text","text":{"content":"70","link":null},"annotations":{"bold":false,"italic":false,"strikethrough":false,"underline":false,"code":false,"color":"default"},"plain_text":"70","href":null}],[{"type":"text","text":{"content":"10200","link":null},"annotations":{"bold":false,"italic":false,"strikethrough":false,"underline":false,"code":false,"color":"default"},"plain_text":"10200","href":null}],[{"type":"text","text":{"content":"161A2","link":null},"annotations":{"bold":false,"italic":false,"strikethrough":false,"underline":false,"code":false,"color":"default"},"plain_text":"161A2","href":null}]]},"archived":false},{"object":"block","id":"38034d6d-7cea-818f-bdca-c4a413f1f0c1","parent":{"type":"block_id","block_id":"38034d6d-7cea-8143-990c-f38c5a529acc"},"created_time":"2026-06-15T15:20:00.000Z","last_edited_time":"2026-06-15T15:20:00.000Z","created_by":{"object":"user","id":"35534d6d-7cea-8179-8809-002768bc44c3"},"last_edited_by":{"object":"user","id":"35534d6d-7cea-8179-8809-002768bc44c3"},"has_children":false,"in_trash":false,"type":"table_row","table_row":{"cells":[[{"type":"text","text":{"content":"15R19.5","link":null},"annotations":{"bold":false,"italic":false,"strikethrough":false,"underline":false,"code":false,"color":"default"},"plain_text":"15R19.5","href":null}],[{"type":"text","text":{"content":"TL","link":null},"annotations":{"bold":false,"italic":false,"strikethrough":false,"underline":false,"code":false,"color":"default"},"plain_text":"TL","href":null}],[{"type":"text","text":{"content":"11.75","link":null},"annotations":{"bold":false,"italic":false,"strikethrough":false,"underline":false,"code":false,"color":"default"},"plain_text":"11.75","href":null}],[{"type":"text","text":{"content":"1019","link":null},"annotations":{"bold":false,"italic":false,"strikethrough":false,"underline":false,"code":false,"color":"default"},"plain_text":"1019","href":null}],[{"type":"text","text":{"content":"389","link":null},"annotations":{"bold":false,"italic":false,"strikethrough":false,"underline":false,"code":false,"color":"default"},"plain_text":"389","href":null}],[{"type":"text","text":{"content":"26","link":null},"annotations":{"bold":false,"italic":false,"strikethrough":false,"underline":false,"code":false,"color":"default"},"plain_text":"26","href":null}],[{"type":"text","text":{"content":"10","link":null},"annotations":{"bold":false,"italic":false,"strikethrough":false,"underline":false,"code":false,"color":"default"},"plain_text":"10","href":null}],[{"type":"text","text":{"content":"480","link":null},"annotations":{"bold":false,"italic":false,"strikethrough":false,"underline":false,"code":false,"color":"default"},"plain_text":"480","href":null}],[{"type":"text","text":{"content":"4625","link":null},"annotations":{"bold":false,"italic":false,"strikethrough":false,"underline":false,"code":false,"color":"default"},"plain_text":"4625","href":null}],[{"type":"text","text":{"content":"161A2","link":null},"annotations":{"bold":false,"italic":false,"strikethrough":false,"underline":false,"code":false,"color":"default"},"plain_text":"161A2","href":null}]]},"archived":false}]},{"object":"block","id":"38034d6d-7cea-8169-a190-c621f75b07ad","parent":{"type":"page_id","page_id":"38034d6d-7cea-81bd-9ff4-ff0a324e4d5a"},"created_time":"2026-06-15T15:20:00.000Z","last_edited_time":"2026-06-15T15:20:00.000Z","created_by":{"object":"user","id":"35534d6d-7cea-8179-8809-002768bc44c3"},"last_edited_by":{"object":"user","id":"35534d6d-7cea-8179-8809-002768bc44c3"},"has_children":false,"in_trash":false,"type":"heading_2","heading_2":{"rich_text":[{"type":"text","text":{"content":"Gallery","link":null},"annotations":{"bold":false,"italic":false,"strikethrough":false,"underline":false,"code":false,"color":"default"},"plain_text":"Gallery","href":null}],"is_toggleable":false,"color":"default"},"archived":false},{"object":"block","id":"38034d6d-7cea-8126-81ca-f97e6a69bef6","parent":{"type":"page_id","page_id":"38034d6d-7cea-81bd-9ff4-ff0a324e4d5a"},"created_time":"2026-06-15T15:20:00.000Z","last_edited_time":"2026-06-15T15:20:00.000Z","created_by":{"object":"user","id":"35534d6d-7cea-8179-8809-002768bc44c3"},"last_edited_by":{"object":"user","id":"35534d6d-7cea-8179-8809-002768bc44c3"},"has_children":false,"in_trash":false,"type":"image","image":{"caption":[],"type":"external","external":{"url":"https://maxamtire.com/wp-content/uploads/2023/10/230306_Maxam-Tire_MS906R_FINAL-scaled-2.jpg"}},"archived":false},{"object":"block","id":"38034d6d-7cea-8108-a5c4-ea4aac3ccfae","parent":{"type":"page_id","page_id":"38034d6d-7cea-81bd-9ff4-ff0a324e4d5a"},"created_time":"2026-06-15T15:20:00.000Z","last_edited_time":"2026-06-15T15:20:00.000Z","created_by":{"object":"user","id":"35534d6d-7cea-8179-8809-002768bc44c3"},"last_edited_by":{"object":"user","id":"35534d6d-7cea-8179-8809-002768bc44c3"},"has_children":false,"in_trash":false,"type":"image","image":{"caption":[],"type":"external","external":{"url":"https://maxamtire.com/wp-content/uploads/2023/10/230306_Maxam-Tire_MS906R_TREAD_FINAL.png"}},"archived":false}]